libp2p/main.py
libp2p/mdns.py
libp2p/pubsub.py
libp2p/dht.py
libp2p/ping.py
libp2p/__init__.py
libp2p/cid.py
libp2p/routed_host.py
libp2p/peer.py
libp2p/utils.py
libp2p/data_store.py
libp2p/peer_store.py
libp2p/crypto.py
libp2p/client.py
libp2p/routing.py
libp2p/validator.py
libp2p/conn_mgr.py
libp2p/relay.py
libp2p/bin/libp2p-linux_x86_64.so
libp2p_go-0.1.4.dist-info/WHEEL
libp2p_go-0.1.4.dist-info/RECORD
libp2p_go-0.1.4.dist-info/METADATA
libp2p_go-0.1.4.dist-info/licenses/LICENSE
