Metadata-Version: 2.1
Name: libp2p-go
Version: 0.1.4
License: MIT
Author-email: songwei <github@songwei.io>
Requires-Python: >=3.11
Requires-Dist: msgpack>=1.0.4
Requires-Dist: multiaddr>=0.0.9
Provides-Extra: build
Requires-Dist: auditwheel>=5.3.0; extra == "build"
Provides-Extra: test
Requires-Dist: coverage>=6.3.2; extra == "test"
Requires-Dist: pytest>=7.1.0; extra == "test"
Requires-Dist: pytest-asyncio>=0.20.3; extra == "test"
Requires-Dist: pytest-cov>=4.0.0; extra == "test"
